README.md
setup.py
id_document_validator.egg-info/PKG-INFO
id_document_validator.egg-info/SOURCES.txt
id_document_validator.egg-info/dependency_links.txt
id_document_validator.egg-info/top_level.txt
tests/__init__.py
validator/__init__.py
validator/validator.py