Metadata-Version: 1.2
Name: id-document-validator
Version: 0.0.1
Summary: A simple Identity Document Characters Validator (just for DNI and cedula identity documents)
Home-page: https://github.com/greatBrain/id_document_validator
Author: Erick M. Fana (roy-mustang)
Author-email: efanaportes@gmail.com
License: UNKNOWN
Platform: UNKNOWN
Classifier: Programming Language :: Python :: 3.7
Classifier: License :: OSI Approved :: MIT License
Classifier: Operating System :: OS Independent
Requires-Python: >=3.7
